buildout.cfg
setup.py
src/megrok/__init__.py
src/megrok.form.egg-info/PKG-INFO
src/megrok.form.egg-info/SOURCES.txt
src/megrok.form.egg-info/dependency_links.txt
src/megrok.form.egg-info/entry_points.txt
src/megrok.form.egg-info/namespace_packages.txt
src/megrok.form.egg-info/not-zip-safe
src/megrok.form.egg-info/requires.txt
src/megrok.form.egg-info/top_level.txt
src/megrok/form/CHANGES.txt
src/megrok/form/README.txt
src/megrok/form/TODO.txt
src/megrok/form/__init__.py
src/megrok/form/browser.py
src/megrok/form/configure.zcml
src/megrok/form/constraints.py
src/megrok/form/fields.py
src/megrok/form/ftesting.zcml
src/megrok/form/interfaces.py
src/megrok/form/overrides.zcml
src/megrok/form/tinydisplaywidget.pt
src/megrok/form/widgets.py
src/megrok/form/tests/__init__.py
src/megrok/form/tests/test_constraints.py
src/megrok/form/tests/test_form.py