Metadata-Version: 1.0
Name: megrok.form
Version: 0.2.3
Summary: Fields, Widgets and Constraints for Grok
Home-page: http://svn.zope.org/megrok.form
Author: Dirceu Pereira Tiegs
Author-email: dirceutiegs@gmail.com
License: ZPL
Keywords: grok form widgets fields constraints
Platform: UNKNOWN
Classifier: Development Status :: 3 - Alpha
Classifier: Environment :: Web Environment
Classifier: Intended Audience :: Developers
Classifier: License :: OSI Approved :: Zope Public License
Classifier: Programming Language :: Python
Classifier: Operating System :: OS Independent
Classifier: Topic :: Internet :: WWW/HTTP
